DjangoKuangjiaJichujiaochengCYuyanBianchengWangFix1/README.md
DjangoKuangjiaJichujiaochengCYuyanBianchengWangFix1/__init__.py
DjangoKuangjiaJichujiaochengCYuyanBianchengWangFix1/__main__.py
DjangoKuangjiaJichujiaochengCYuyanBianchengWangFix1/file.epub
DjangoKuangjiaJichujiaochengCYuyanBianchengWangFix1/index.html
DjangoKuangjiaJichujiaochengCYuyanBianchengWangFix1/css/__init__.py
DjangoKuangjiaJichujiaochengCYuyanBianchengWangFix1/css/annotations.css
DjangoKuangjiaJichujiaochengCYuyanBianchengWangFix1/css/main.css
DjangoKuangjiaJichujiaochengCYuyanBianchengWangFix1/css/normalize.css
DjangoKuangjiaJichujiaochengCYuyanBianchengWangFix1/css/popup.css
DjangoKuangjiaJichujiaochengCYuyanBianchengWangFix1/font/__init__.py
DjangoKuangjiaJichujiaochengCYuyanBianchengWangFix1/font/fontello.eot
DjangoKuangjiaJichujiaochengCYuyanBianchengWangFix1/font/fontello.svg
DjangoKuangjiaJichujiaochengCYuyanBianchengWangFix1/font/fontello.ttf
DjangoKuangjiaJichujiaochengCYuyanBianchengWangFix1/font/fontello.woff
DjangoKuangjiaJichujiaochengCYuyanBianchengWangFix1/img/__init__.py
DjangoKuangjiaJichujiaochengCYuyanBianchengWangFix1/img/annotator-glyph-sprite.png
DjangoKuangjiaJichujiaochengCYuyanBianchengWangFix1/img/annotator-icon-sprite.png
DjangoKuangjiaJichujiaochengCYuyanBianchengWangFix1/img/apple-touch-icon.png
DjangoKuangjiaJichujiaochengCYuyanBianchengWangFix1/img/cancelfullscreen.png
DjangoKuangjiaJichujiaochengCYuyanBianchengWangFix1/img/close.png
DjangoKuangjiaJichujiaochengCYuyanBianchengWangFix1/img/fullscreen.png
DjangoKuangjiaJichujiaochengCYuyanBianchengWangFix1/img/loader.gif
DjangoKuangjiaJichujiaochengCYuyanBianchengWangFix1/img/menu-icon.png
DjangoKuangjiaJichujiaochengCYuyanBianchengWangFix1/img/save.png
DjangoKuangjiaJichujiaochengCYuyanBianchengWangFix1/img/saved.png
DjangoKuangjiaJichujiaochengCYuyanBianchengWangFix1/img/settings-s.png
DjangoKuangjiaJichujiaochengCYuyanBianchengWangFix1/img/settings.png
django_kuangjia_jichujiaocheng_c_yuyan_biancheng_wang_fix1-2025.3.24.0.dist-info/METADATA
django_kuangjia_jichujiaocheng_c_yuyan_biancheng_wang_fix1-2025.3.24.0.dist-info/WHEEL
django_kuangjia_jichujiaocheng_c_yuyan_biancheng_wang_fix1-2025.3.24.0.dist-info/entry_points.txt
django_kuangjia_jichujiaocheng_c_yuyan_biancheng_wang_fix1-2025.3.24.0.dist-info/top_level.txt
django_kuangjia_jichujiaocheng_c_yuyan_biancheng_wang_fix1-2025.3.24.0.dist-info/RECORD
